LICENSE
MANIFEST.in
README.rst
pyproject.toml
setup.cfg
./src/striebel.bib.egg-info/PKG-INFO
./src/striebel.bib.egg-info/SOURCES.txt
./src/striebel.bib.egg-info/dependency_links.txt
./src/striebel.bib.egg-info/entry_points.txt
./src/striebel.bib.egg-info/top_level.txt
src/striebel.bib.egg-info/PKG-INFO
src/striebel.bib.egg-info/SOURCES.txt
src/striebel.bib.egg-info/dependency_links.txt
src/striebel.bib.egg-info/entry_points.txt
src/striebel.bib.egg-info/top_level.txt
src/striebel/bib/__init__.py
src/striebel/bib/__main__.py
src/striebel/bib/meta.py
src/striebel/bib/meta.sh
src/striebel/bib/data/hello.txt