Metadata-Version: 2.1
Name: striebel.bib
Version: 0.0.1
Summary: Stub files to use as the basis of a Python project that can be packaged and uploaded to PyPI
Home-page: https://github.com/striebel/striebel.bib
Author: Jacob Striebel
Author-email: jacob.striebel@example.com
License: MIT
Project-URL: Source, https://github.com/striebel/striebel.bib
License-File: LICENSE
